socialbakers/__init__.py
socialbakers/api.py
socialbakers/apiconfig.py
socialbakers/urls.py
socialbakers/objects/__init__.py
socialbakers/objects/socialbakerspost.py
socialbakers/objects/socialnetworkobject.py
socialbakers/tests/__init__.py
socialbakers/tests/test_api.py
socialbakers-0.2.3.dist-info/DESCRIPTION.rst
socialbakers-0.2.3.dist-info/METADATA
socialbakers-0.2.3.dist-info/RECORD
socialbakers-0.2.3.dist-info/WHEEL
socialbakers-0.2.3.dist-info/metadata.json
socialbakers-0.2.3.dist-info/top_level.txt
