Metadata-Version: 2.0
Name: socialbakers
Version: 0.2.3
Summary: This Wrapper for Socialbaker API
Home-page: https://juanpa_findasense@bitbucket.org/juanpa_findasense/socialbakers
Author: Findasense Intelligence
Author-email: juanpablo@findasense.com
License: MIT
Keywords: socialbakers socialmedia
Platform: UNKNOWN
Classifier: Development Status :: 3 - Alpha
Classifier: Intended Audience :: Developers
Classifier: Topic :: Software Development :: Build Tools
Classifier: License :: OSI Approved :: MIT License
Classifier: Programming Language :: Python :: 2
Classifier: Programming Language :: Python :: 2.6
Classifier: Programming Language :: Python :: 2.7
